LICENSE.txt
MANIFEST.in
README.rst
setup.py
test_junit_xml.py
tox.ini
junit_xml/__init__.py
junit_xml.egg-info/PKG-INFO
junit_xml.egg-info/SOURCES.txt
junit_xml.egg-info/dependency_links.txt
junit_xml.egg-info/requires.txt
junit_xml.egg-info/top_level.txt