Metadata-Version: 1.1
Name: junit-xml
Version: 1.7
Summary: Creates JUnit XML test result documents that can be read by tools such as Jenkins
Home-page: https://github.com/kyrus/python-junit-xml
Author: Brian Beyer
Author-email: brian@kyr.us
License: MIT
Platform: UNKNOWN
Classifier: Development Status :: 5 - Production/Stable
Classifier: Intended Audience :: Developers
Classifier: License :: Freely Distributable
Classifier: License :: OSI Approved :: MIT License
Classifier: Operating System :: OS Independent
Classifier: Programming Language :: Python
Classifier: Programming Language :: Python :: 3
Classifier: Topic :: Software Development :: Build Tools
Classifier: Topic :: Software Development :: Testing
